[
  {
    "schemaVersion": "s7-0.1.0",
    "bossNodeId": "n060",
    "mainProblemTag": "swarm",
    "templateRef": "t02",
    "secondaryPressureTag": "none",
    "previewTagRefs": [],
    "forbiddenMechanicTag": "no_shield_backline_summon_burst_berserk"
  },
  {
    "schemaVersion": "s7-0.1.0",
    "bossNodeId": "n084",
    "mainProblemTag": "shield",
    "templateRef": "t04",
    "secondaryPressureTag": "none",
    "previewTagRefs": [],
    "forbiddenMechanicTag": "no_backline_summon_burst_berserk"
  },
  {
    "schemaVersion": "s7-0.1.0",
    "bossNodeId": "n102",
    "mainProblemTag": "backline",
    "templateRef": "t06",
    "secondaryPressureTag": "none",
    "previewTagRefs": [],
    "forbiddenMechanicTag": "no_summon_burst_berserk"
  },
  {
    "schemaVersion": "s7-0.1.0",
    "bossNodeId": "n120",
    "mainProblemTag": "summon",
    "templateRef": "t09",
    "secondaryPressureTag": "none",
    "previewTagRefs": [],
    "forbiddenMechanicTag": "no_burst_berserk"
  },
  {
    "schemaVersion": "s7-0.1.0",
    "bossNodeId": "n138",
    "mainProblemTag": "burst",
    "templateRef": "t08",
    "secondaryPressureTag": "none",
    "previewTagRefs": [],
    "forbiddenMechanicTag": "no_berserk"
  },
  {
    "schemaVersion": "s7-0.1.0",
    "bossNodeId": "n150",
    "mainProblemTag": "berserk",
    "templateRef": "t10",
    "secondaryPressureTag": "none",
    "previewTagRefs": [],
    "forbiddenMechanicTag": "all_mechanics_allowed"
  },
  {
    "schemaVersion": "s7-0.1.0",
    "bossNodeId": "n030",
    "mainProblemTag": "swarm",
    "templateRef": "t02",
    "secondaryPressureTag": "none",
    "previewTagRefs": [],
    "forbiddenMechanicTag": "no_shield_backline_summon_burst_berserk"
  }
]
